avoc/AVoc.desktop
avoc/AVoc.svg
avoc/__init__.py
avoc/actioncheckbox.py
avoc/audiobackends.py
avoc/audiopipewire.py
avoc/audiopipewiresettings.py
avoc/audioqtmultimedia.py
avoc/audioqtmultimediadevices.py
avoc/audioqtmultimediasettings.py
avoc/customizeui.py
avoc/exceptionhook.py
avoc/exceptions.py
avoc/handletooltipslider.py
avoc/loadingoverlay.py
avoc/main.py
avoc/modelsettings.py
avoc/processingsettings.py
avoc/voicecardsmanager.py
avoc/windowarea.py
avoc-0.1.1.dist-info/licenses/LICENSE
avoc-0.1.1.dist-info/METADATA
avoc-0.1.1.dist-info/WHEEL
avoc-0.1.1.dist-info/entry_points.txt
avoc-0.1.1.dist-info/top_level.txt
avoc-0.1.1.dist-info/RECORD
