Metadata-Version: 2.4
Name: avoc
Version: 0.1.1
Summary: Voice changer for desktop
Author-email: develOseven <devel.oseven@gmail.com>
License-Expression: MIT
Project-URL: Homepage, https://github.com/develOseven/avoc
Project-URL: Issues, https://github.com/develOseven/avoc/issues
Classifier: Programming Language :: Python :: 3
Classifier: Operating System :: OS Independent
License-File: LICENSE
Requires-Dist: pipewire-filtertools>=0.2.0; sys_platform == "linux"
Requires-Dist: PySide6
Requires-Dist: PySide6-GlobalHotkeys
Requires-Dist: voiceconversion>=0.0.8
Provides-Extra: dev
Requires-Dist: pytest-qt; extra == "dev"
Dynamic: license-file
